MANIFEST.in
README.md
gitshelve.py
setup.cfg
setup.py
gitshelve.egg-info/PKG-INFO
gitshelve.egg-info/SOURCES.txt
gitshelve.egg-info/dependency_links.txt
gitshelve.egg-info/top_level.txt
test/test_gitshelve.py