Metadata-Version: 1.1
Name: gitshelve
Version: 0.1.1
Summary: Python object for easily writing scripts that store arbitrary data inside a Git repository.
Home-page: https://github.com/tstone2077/gitshelve
Author: John Wiegley, Thurston Stone
Author-email: tstone2077@gmail.com
License: UNKNOWN
Platform: UNKNOWN
Classifier: Development Status :: 3 - Alpha
Classifier: Programming Language :: Python :: 2
Classifier: Programming Language :: Python :: 3
Classifier: Intended Audience :: Developers
Classifier: Topic :: Software Development :: Libraries
Classifier: Operating System :: OS Independent
Classifier: License :: OSI Approved :: BSD License
